kzutil/__init__.py
kzutil/consts.py
kzutil/emailing.py
kzutil/wrappers.py
kzutil/zip.py
kzutil-1.1.6.dist-info/METADATA
kzutil-1.1.6.dist-info/WHEEL
kzutil-1.1.6.dist-info/top_level.txt
kzutil-1.1.6.dist-info/RECORD
